<openBVE xmlns:xsi="http://www.w3.org/2001/XMLSchema-instance" xmlns:xsd="http://www.w3.org/2001/XMLSchema">
  <RoutePatches>
	<Patch>
		<Hash>8052F76CB2EFA58514334C2E16714BAEDF1BEE6EEC90A84555C76C09C266E787</Hash>
		<FileName>S75 daytime.csv</FileName>
		<SignalSet>SV.xml</SignalSet>
	</Patch>
	<Patch>
		<Hash>BB3EC7F141DB94660E96F52D654CD7163D8F69451376F09CBF956535729C0798</Hash>
		<FileName>Tram_NeustadtL4_v2.rw</FileName>
		<ReducedColorTransparency>true</ReducedColorTransparency>
		<AccurateObjectDisposal>true</AccurateObjectDisposal>
	</Patch>
  </RoutePatches>
</openBVE>